odoo/addons/product_firmware_version/README.rst
odoo/addons/product_firmware_version/__init__.py
odoo/addons/product_firmware_version/__manifest__.py
odoo/addons/product_firmware_version/i18n/ca.po
odoo/addons/product_firmware_version/i18n/de.po
odoo/addons/product_firmware_version/i18n/es.po
odoo/addons/product_firmware_version/i18n/fr.po
odoo/addons/product_firmware_version/i18n/hr.po
odoo/addons/product_firmware_version/i18n/it.po
odoo/addons/product_firmware_version/i18n/nl_NL.po
odoo/addons/product_firmware_version/i18n/product_firmware_version.pot
odoo/addons/product_firmware_version/i18n/sl.po
odoo/addons/product_firmware_version/models/__init__.py
odoo/addons/product_firmware_version/models/product.py
odoo/addons/product_firmware_version/readme/CONTRIBUTORS.rst
odoo/addons/product_firmware_version/readme/DESCRIPTION.rst
odoo/addons/product_firmware_version/readme/USAGE.rst
odoo/addons/product_firmware_version/static/description/icon.png
odoo/addons/product_firmware_version/static/description/index.html
odoo/addons/product_firmware_version/views/product_view.xml
odoo12_addon_product_firmware_version-12.0.1.0.0.99.dev10.dist-info/METADATA
odoo12_addon_product_firmware_version-12.0.1.0.0.99.dev10.dist-info/WHEEL
odoo12_addon_product_firmware_version-12.0.1.0.0.99.dev10.dist-info/top_level.txt
odoo12_addon_product_firmware_version-12.0.1.0.0.99.dev10.dist-info/RECORD
